checkopt/__init__.py
checkopt-1.0.0.dist-info/LICENSE
checkopt-1.0.0.dist-info/METADATA
checkopt-1.0.0.dist-info/WHEEL
checkopt-1.0.0.dist-info/top_level.txt
checkopt-1.0.0.dist-info/RECORD
