Metadata-Version: 2.1
Name: checkopt
Version: 1.0.0
Summary: ✨A powerful tool to replace getopt✨
Home-page: https://github.com/yixinNB/checkopt
Author: y
Project-URL: Documentation, https://github.com/yixinNB/checkopt
Project-URL: Code, https://github.com/yixinNB/checkopt
Project-URL: Issue tracker, https://github.com/yixinNB/checkopt/issues
License-File: LICENSE
